inford/__init__.py
inford/module.py
inford/presets.py
inford-1.1.0.dist-info/LICENCE
inford-1.1.0.dist-info/METADATA
inford-1.1.0.dist-info/WHEEL
inford-1.1.0.dist-info/top_level.txt
inford-1.1.0.dist-info/RECORD
