Metadata-Version: 2.1
Name: inford
Version: 1.1.0
Summary: Simple module for sending dsicord webhooks
Home-page: https://github.com/Prathamesh-B/inford
Author: Prathamesh Bhaleakr
Author-email: prathameshb1704@gmail.com
License: MIT License
Platform: UNKNOWN
Classifier: Environment :: Web Environment
Classifier: License :: OSI Approved :: MIT License
Classifier: Operating System :: OS Independent
Classifier: Programming Language :: Python
Classifier: Programming Language :: Python :: 3.6
Classifier: Programming Language :: Python :: 3.7
Classifier: Programming Language :: Python :: 3.8
Classifier: Programming Language :: Python :: 3.9
Requires-Python: >=3.6
License-File: LICENCE
Requires-Dist: requests (>=2.19.1)
